fds/__init__.py
fds/sdk/__init__.py
fds/sdk/FactSetRBICS/__init__.py
fds/sdk/FactSetRBICS/api_client.py
fds/sdk/FactSetRBICS/configuration.py
fds/sdk/FactSetRBICS/exceptions.py
fds/sdk/FactSetRBICS/model_utils.py
fds/sdk/FactSetRBICS/rest.py
fds/sdk/FactSetRBICS/api/__init__.py
fds/sdk/FactSetRBICS/api/entity_focus_api.py
fds/sdk/FactSetRBICS/api/structure_api.py
fds/sdk/FactSetRBICS/apis/__init__.py
fds/sdk/FactSetRBICS/model/__init__.py
fds/sdk/FactSetRBICS/model/entity_focus.py
fds/sdk/FactSetRBICS/model/entity_focus_request.py
fds/sdk/FactSetRBICS/model/entity_focus_response.py
fds/sdk/FactSetRBICS/model/error_response.py
fds/sdk/FactSetRBICS/model/error_response_sub_errors.py
fds/sdk/FactSetRBICS/model/ids.py
fds/sdk/FactSetRBICS/model/level_structure.py
fds/sdk/FactSetRBICS/model/levels.py
fds/sdk/FactSetRBICS/model/rbics_ids.py
fds/sdk/FactSetRBICS/model/structure.py
fds/sdk/FactSetRBICS/model/structure_request.py
fds/sdk/FactSetRBICS/model/structure_response.py
fds/sdk/FactSetRBICS/models/__init__.py
fds.sdk.FactSetRBICS-1.0.3.dist-info/LICENSE
fds.sdk.FactSetRBICS-1.0.3.dist-info/METADATA
fds.sdk.FactSetRBICS-1.0.3.dist-info/WHEEL
fds.sdk.FactSetRBICS-1.0.3.dist-info/top_level.txt
fds.sdk.FactSetRBICS-1.0.3.dist-info/RECORD
